{
  "name": {
    "tr": "Ödüller",
    "en": "Awards",
    "de": "Auszeichnungen",
    "ru": "Награды"
  },
  "status": "play",
  "category": "",
  "id": "oduller",
  "url": "",
  "path": "oduller",
  "index": 4,
  "desing": {
    "header": [],
    "body": [],
    "footer": []
  },
  "pathnext": "",
  "description": {
    "tr": "En iyi poster ödülü: Chlamydia pneumonia ompA Gene DNA (2nd Molecular and Diagnostic Microbiology Congress, 2002 Kemer-Antalya). Trabzon Valiliğince verilen takdirname. bilgi.text.",
    "en": "Best poster award: Chlamydia pneumonia ompA Gene DNA (2nd Molecular and Diagnostic Microbiology Congress, 2002 Kemer-Antalya). Letter of commendation from Governorship of Trabzon.",
    "de": "Bester Poster-Preis: Chlamydia pneumonia ompA Gene DNA (2. Molecular and Diagnostic Microbiology Congress, 2002 Kemer-Antalya). Lobesbrief der Provinz Trabzon.",
    "ru": "Награда за лучший постер: Chlamydia pneumonia ompA Gene DNA (2-й конгресс молекулярной и диагностической микробиологии, 2002 Кемер-Анталья). Благодарность от губернаторства Трабзона."
  },
  "desc": {},
  "keyword": {
    "tr": "",
    "en": "",
    "de": "",
    "ru": ""
  },
  "text": {
    "tr": "",
    "en": "",
    "de": "",
    "ru": ""
  },
  "update": "2026-02-09T08:22:44.884Z",
  "date": "2026-02-09T06:37:04.298Z"
}